sariSparqlParser/__init__.py
sari_sparql_parser-0.0.6.dist-info/METADATA
sari_sparql_parser-0.0.6.dist-info/WHEEL
sari_sparql_parser-0.0.6.dist-info/top_level.txt
sari_sparql_parser-0.0.6.dist-info/RECORD
