Metadata-Version: 2.1
Name: sari-sparql-parser
Version: 0.0.6
Summary: A library for parsing SPARQL queries and updates
Home-page: https://github.com/swiss-art-research-net/sari-sparql-parser.git
Author: Florian Kräutli
Author-email: florian.kraeutli@uzh.ch
License: UNKNOWN
Platform: UNKNOWN
Classifier: Programming Language :: Python :: 3
Classifier: License :: OSI Approved :: MIT License
Classifier: Operating System :: OS Independent
Requires-Python: >=3.6
Requires-Dist: rdflib
Requires-Dist: pyparsing
